comparator_2bit.vhd
library IEEE;
use IEEE.STD_LOGIC_1164.ALL;

entity comparator_2bit is
    port (
        A : in std_logic_vector(1 downto 0);
        B : in std_logic_vector(1 downto 0);
        GT : out std_logic;
        LT : out std_logic;
        EQ : out std_logic
    );
end comparator_2bit;

architecture behavioral of comparator_2bit is 
    begin
        -- A > B
        GT <= (A(1) and not B(1)) or 
            ((A(1) xnor B(1)) and A(0) and not B(0));
        -- A < B
        LT <= (not A(1) and B(1)) or
            ((A(1) xnor B(1)) and not A(0) and B(0));

        -- A = B
        EQ <= (A(1) xnor B(1)) and
            (A(0) xnor B(0));
    end behavioral;

comparator_2bit_tb.vhd
library IEEE;
use IEEE.STD_LOGIC_1164.ALL;

entity comparator_2bit_tb is
end comparator_2bit_tb;

architecture test of comparator_2bit_tb is

    component comparator_2bit
        port (
            A  : in  std_logic_vector(1 downto 0);
            B  : in  std_logic_vector(1 downto 0);
            GT : out std_logic;
            LT : out std_logic;
            EQ : out std_logic
        );
    end component;

    signal A  : std_logic_vector(1 downto 0);
    signal B  : std_logic_vector(1 downto 0);
    signal GT : std_logic;
    signal LT : std_logic;
    signal EQ : std_logic;

begin

    uut: comparator_2bit
        port map (
            A  => A,
            B  => B,
            GT => GT,
            LT => LT,
            EQ => EQ
        );

    process
    begin

        -- A = 00, B = 00
        A <= "00";
        B <= "00";
        wait for 1 ns;

        -- A = 00, B = 01
        A <= "00";
        B <= "01";
        wait for 1 ns;

        -- A = 00, B = 10
        A <= "00";
        B <= "10";
        wait for 1 ns;

        -- A = 00, B = 11
        A <= "00";
        B <= "11";
        wait for 1 ns;


        -- A = 01
        A <= "01";
        B <= "00";
        wait for 1 ns;

        A <= "01";
        B <= "01";
        wait for 1 ns;

        A <= "01";
        B <= "10";
        wait for 1 ns;

        A <= "01";
        B <= "11";
        wait for 1 ns;


        -- A = 10
        A <= "10";
        B <= "00";
        wait for 1 ns;

        A <= "10";
        B <= "01";
        wait for 1 ns;

        A <= "10";
        B <= "10";
        wait for 1 ns;

        A <= "10";
        B <= "11";
        wait for 1 ns;


        -- A = 11
        A <= "11";
        B <= "00";
        wait for 1 ns;

        A <= "11";
        B <= "01";
        wait for 1 ns;

        A <= "11";
        B <= "10";
        wait for 1 ns;

        A <= "11";
        B <= "11";
        wait for 1 ns;

        assert false report "Comparator Test Finished";
        wait;

    end process;

end test;

comparator.vcd
$date
  Tue Oct 06 10:11:01 2026
$end
$version
  GHDL v0
$end
$timescale
  1 fs
$end
$scope module standard $end
$upscope $end
$scope module std_logic_1164 $end
$upscope $end
$scope module comparator_2bit_tb $end
$var reg 2 ! a[1:0] $end
$var reg 2 " b[1:0] $end
$var reg 1 # gt $end
$var reg 1 $ lt $end
$var reg 1 % eq $end
$scope module uut $end
$var reg 2 & a[1:0] $end
$var reg 2 ' b[1:0] $end
$var reg 1 ( gt $end
$var reg 1 ) lt $end
$var reg 1 * eq $end
$upscope $end
$upscope $end
$enddefinitions $end
#0
b00 !
b00 "
0#
0$
1%
b00 &
b00 '
0(
0)
1*
#1000000
b01 "
1$
0%
b01 '
1)
0*
#2000000
b10 "
b10 '
#3000000
b11 "
b11 '
#4000000
b01 !
b00 "
1#
0$
b01 &
b00 '
1(
0)
#5000000
b01 "
0#
1%
b01 '
0(
1*
#6000000
b10 "
1$
0%
b10 '
1)
0*
#7000000
b11 "
b11 '
#8000000
b10 !
b00 "
1#
0$
b10 &
b00 '
1(
0)
#9000000
b01 "
b01 '
#10000000
b10 "
0#
1%
b10 '
0(
1*
#11000000
b11 "
1$
0%
b11 '
1)
0*
#12000000
b11 !
b00 "
1#
0$
b11 &
b00 '
1(
0)
#13000000
b01 "
b01 '
#14000000
b10 "
b10 '
#15000000
b11 "
0#
1%
b11 '
0(
1*
