mux4to1.vhd
library IEEE;
use IEEE.STD_LOGIC_1164.ALL;

entity mux4to1 is
    port (
        I0 : in  std_logic;
        I1 : in  std_logic;
        I2 : in  std_logic;
        I3 : in  std_logic;
        S  : in  std_logic_vector(1 downto 0);
        Y  : out std_logic
    );
end mux4to1;

architecture behavioral of mux4to1 is
begin

    process(I0, I1, I2, I3, S)
    begin
        case S is
            when "00" =>
                Y <= I0;

            when "01" =>
                Y <= I1;

            when "10" =>
                Y <= I2;

            when "11" =>
                Y <= I3;

            when others =>
                Y <= 'X';
        end case;
    end process;

end behavioral;

mux4to1_tb.vhd
library IEEE;
use IEEE.STD_LOGIC_1164.ALL;

entity mux4to1_tb is
end mux4to1_tb;

architecture test of mux4to1_tb is

    component mux4to1
        port (
            I0 : in  std_logic;
            I1 : in  std_logic;
            I2 : in  std_logic;
            I3 : in  std_logic;
            S  : in  std_logic_vector(1 downto 0);
            Y  : out std_logic
        );
    end component;

    signal I0 : std_logic;
    signal I1 : std_logic;
    signal I2 : std_logic;
    signal I3 : std_logic;
    signal S  : std_logic_vector(1 downto 0);
    signal Y  : std_logic;

begin

    uut: mux4to1
        port map (
            I0 => I0,
            I1 => I1,
            I2 => I2,
            I3 => I3,
            S  => S,
            Y  => Y
        );

    process
    begin

        -- Data inputs
        I0 <= '0';
        I1 <= '1';
        I2 <= '0';
        I3 <= '1';

        -- Select I0
        S <= "00";
        wait for 1 ns;

        -- Select I1
        S <= "01";
        wait for 1 ns;

        -- Select I2
        S <= "10";
        wait for 1 ns;

        -- Select I3
        S <= "11";
        wait for 1 ns;


        -- Change data inputs
        I0 <= '1';
        I1 <= '0';
        I2 <= '1';
        I3 <= '0';

        S <= "00";
        wait for 1 ns;

        S <= "01";
        wait for 1 ns;

        S <= "10";
        wait for 1 ns;

        S <= "11";
        wait for 1 ns;

        assert false report "MUX 4:1 Test Finished";
        wait;

    end process;

end test;

mux4.vcd
$date
  Tue Oct 06 10:32:44 2026
$end
$version
  GHDL v0
$end
$timescale
  1 fs
$end
$scope module standard $end
$upscope $end
$scope module std_logic_1164 $end
$upscope $end
$scope module mux4to1_tb $end
$var reg 1 ! i0 $end
$var reg 1 " i1 $end
$var reg 1 # i2 $end
$var reg 1 $ i3 $end
$var reg 2 % s[1:0] $end
$var reg 1 & y $end
$scope module uut $end
$var reg 1 ' i0 $end
$var reg 1 ( i1 $end
$var reg 1 ) i2 $end
$var reg 1 * i3 $end
$var reg 2 + s[1:0] $end
$var reg 1 , y $end
$upscope $end
$upscope $end
$enddefinitions $end
#0
0!
1"
0#
1$
b00 %
0&
0'
1(
0)
1*
b00 +
0,
#1000000
b01 %
1&
b01 +
1,
#2000000
b10 %
0&
b10 +
0,
#3000000
b11 %
1&
b11 +
1,
#4000000
1!
0"
1#
0$
b00 %
1'
0(
1)
0*
b00 +
#5000000
b01 %
0&
b01 +
0,
#6000000
b10 %
1&
b10 +
1,
#7000000
b11 %
0&
b11 +
0,
