mux2to1.vhd
library IEEE;
use IEEE.STD_LOGIC_1164.ALL;

entity mux2to1 is
    port (
        I0 : in  std_logic;
        I1 : in  std_logic;
        S  : in  std_logic;
        Y  : out std_logic
    );
end mux2to1;

architecture behavioral of mux2to1 is
begin

    process(I0, I1, S)
    begin

        if S = '0' then
            Y <= I0;
        else
            Y <= I1;
        end if;

    end process;

end behavioral;

mux4to1.vhd
library IEEE;
use IEEE.STD_LOGIC_1164.ALL;

entity mux4to1 is
    port (
        I0 : in  std_logic;
        I1 : in  std_logic;
        I2 : in  std_logic;
        I3 : in  std_logic;
        S  : in  std_logic_vector(1 downto 0);
        Y  : out std_logic
    );
end mux4to1;

architecture behavioral of mux4to1 is
begin

    process(I0, I1, I2, I3, S)
    begin
        case S is
            when "00" =>
                Y <= I0;

            when "01" =>
                Y <= I1;

            when "10" =>
                Y <= I2;

            when "11" =>
                Y <= I3;

            when others =>
                Y <= 'X';
        end case;
    end process;

end behavioral;

mux8to1.vhd
library IEEE;
use IEEE.STD_LOGIC_1164.ALL;

entity mux8to1 is
    port (
        I0 : in  std_logic;
        I1 : in  std_logic;
        I2 : in  std_logic;
        I3 : in  std_logic;
        I4 : in  std_logic;
        I5 : in  std_logic;
        I6 : in  std_logic;
        I7 : in  std_logic;
        S  : in  std_logic_vector(2 downto 0);
        Y  : out std_logic
    );
end mux8to1;

architecture structural of mux8to1 is

    component mux4to1
        port (
            I0 : in  std_logic;
            I1 : in  std_logic;
            I2 : in  std_logic;
            I3 : in  std_logic;
            S  : in  std_logic_vector(1 downto 0);
            Y  : out std_logic
        );
    end component;

    component mux2to1
        port (
            I0 : in  std_logic;
            I1 : in  std_logic;
            S  : in  std_logic;
            Y  : out std_logic
        );
    end component;

    signal Y0 : std_logic;
    signal Y1 : std_logic;

begin

    -- MUX 4:1 pertama
    MUX_A : mux4to1
        port map (
            I0 => I0,
            I1 => I1,
            I2 => I2,
            I3 => I3,
            S  => S(1 downto 0),
            Y  => Y0
        );

    -- MUX 4:1 kedua
    MUX_B : mux4to1
        port map (
            I0 => I4,
            I1 => I5,
            I2 => I6,
            I3 => I7,
            S  => S(1 downto 0),
            Y  => Y1
        );

    -- MUX 2:1 terakhir
    MUX_C : mux2to1
        port map (
            I0 => Y0,
            I1 => Y1,
            S  => S(2),
            Y  => Y
        );

end structural;

mux8to1_tb.vhd
library IEEE;
use IEEE.STD_LOGIC_1164.ALL;

entity mux8to1_tb is
end mux8to1_tb;

architecture test of mux8to1_tb is

    component mux8to1
        port (
            I0 : in  std_logic;
            I1 : in  std_logic;
            I2 : in  std_logic;
            I3 : in  std_logic;
            I4 : in  std_logic;
            I5 : in  std_logic;
            I6 : in  std_logic;
            I7 : in  std_logic;
            S  : in  std_logic_vector(2 downto 0);
            Y  : out std_logic
        );
    end component;

    signal I0 : std_logic;
    signal I1 : std_logic;
    signal I2 : std_logic;
    signal I3 : std_logic;
    signal I4 : std_logic;
    signal I5 : std_logic;
    signal I6 : std_logic;
    signal I7 : std_logic;

    signal S : std_logic_vector(2 downto 0);
    signal Y : std_logic;

begin

    uut: mux8to1
        port map (
            I0 => I0,
            I1 => I1,
            I2 => I2,
            I3 => I3,
            I4 => I4,
            I5 => I5,
            I6 => I6,
            I7 => I7,
            S  => S,
            Y  => Y
        );

    process
    begin

        -- Input data
        I0 <= '0';
        I1 <= '1';
        I2 <= '0';
        I3 <= '1';
        I4 <= '0';
        I5 <= '1';
        I6 <= '0';
        I7 <= '1';

        -- Select I0
        S <= "000";
        wait for 1 ns;

        -- Select I1
        S <= "001";
        wait for 1 ns;

        -- Select I2
        S <= "010";
        wait for 1 ns;

        -- Select I3
        S <= "011";
        wait for 1 ns;

        -- Select I4
        S <= "100";
        wait for 1 ns;

        -- Select I5
        S <= "101";
        wait for 1 ns;

        -- Select I6
        S <= "110";
        wait for 1 ns;

        -- Select I7
        S <= "111";
        wait for 1 ns;

        assert false report "MUX 8:1 Test Finished";
        wait;

    end process;

end test;

mux8.vcd
$date
  Tue Oct 06 10:41:04 2026
$end
$version
  GHDL v0
$end
$timescale
  1 fs
$end
$scope module standard $end
$upscope $end
$scope module std_logic_1164 $end
$upscope $end
$scope module mux8to1_tb $end
$var reg 1 ! i0 $end
$var reg 1 " i1 $end
$var reg 1 # i2 $end
$var reg 1 $ i3 $end
$var reg 1 % i4 $end
$var reg 1 & i5 $end
$var reg 1 ' i6 $end
$var reg 1 ( i7 $end
$var reg 3 ) s[2:0] $end
$var reg 1 * y $end
$scope module uut $end
$var reg 1 + i0 $end
$var reg 1 , i1 $end
$var reg 1 - i2 $end
$var reg 1 . i3 $end
$var reg 1 / i4 $end
$var reg 1 0 i5 $end
$var reg 1 1 i6 $end
$var reg 1 2 i7 $end
$var reg 3 3 s[2:0] $end
$var reg 1 4 y $end
$var reg 1 5 y0 $end
$var reg 1 6 y1 $end
$scope module mux_a $end
$var reg 1 7 i0 $end
$var reg 1 8 i1 $end
$var reg 1 9 i2 $end
$var reg 1 : i3 $end
$var reg 2 ; s[1:0] $end
$var reg 1 < y $end
$upscope $end
$scope module mux_b $end
$var reg 1 = i0 $end
$var reg 1 > i1 $end
$var reg 1 ? i2 $end
$var reg 1 @ i3 $end
$var reg 2 A s[1:0] $end
$var reg 1 B y $end
$upscope $end
$scope module mux_c $end
$var reg 1 C i0 $end
$var reg 1 D i1 $end
$var reg 1 E s $end
$var reg 1 F y $end
$upscope $end
$upscope $end
$upscope $end
$enddefinitions $end
#0
0!
1"
0#
1$
0%
1&
0'
1(
b000 )
0*
0+
1,
0-
1.
0/
10
01
12
b000 3
04
05
06
07
18
09
1:
b00 ;
0<
0=
1>
0?
1@
b00 A
0B
0C
0D
0E
0F
#1000000
b001 )
1*
b001 3
14
15
16
b01 ;
1<
b01 A
1B
1C
1D
1F
#2000000
b010 )
0*
b010 3
04
05
06
b10 ;
0<
b10 A
0B
0C
0D
0F
#3000000
b011 )
1*
b011 3
14
15
16
b11 ;
1<
b11 A
1B
1C
1D
1F
#4000000
b100 )
0*
b100 3
04
05
06
b00 ;
0<
b00 A
0B
0C
0D
1E
0F
#5000000
b101 )
1*
b101 3
14
15
16
b01 ;
1<
b01 A
1B
1C
1D
1F
#6000000
b110 )
0*
b110 3
04
05
06
b10 ;
0<
b10 A
0B
0C
0D
0F
#7000000
b111 )
1*
b111 3
14
15
16
b11 ;
1<
b11 A
1B
1C
1D
1F
